mkconf/__init__.py
mkconf/config.py
mkconf/plugin.py
mkconf-0.2.0.dist-info/LICENSE
mkconf-0.2.0.dist-info/METADATA
mkconf-0.2.0.dist-info/WHEEL
mkconf-0.2.0.dist-info/entry_points.txt
mkconf-0.2.0.dist-info/RECORD
