Metadata-Version: 2.1
Name: mkconf
Version: 0.2.0
Summary: Plugin for MKDocs to create conference websites
License: Apache-2.0
Author: Leandro G. Almeida
Author-email: leandro.g.almeida@gmail.com
Requires-Python: >=3.10,<4.0
Classifier: License :: OSI Approved :: Apache Software License
Classifier: Programming Language :: Python :: 3
Classifier: Programming Language :: Python :: 3.10
Classifier: Programming Language :: Python :: 3.11
Requires-Dist: Jinja2 (>=3.1.3,<4.0.0)
Requires-Dist: mkdocs (>=1.5.3,<2.0.0)
